tree2json/__init__.py
tree2json/tree2json.py
tree2json-0.1.4.dist-info/METADATA
tree2json-0.1.4.dist-info/WHEEL
tree2json-0.1.4.dist-info/top_level.txt
tree2json-0.1.4.dist-info/RECORD
