Metadata-Version: 2.1
Name: tree2json
Version: 0.1.4
Summary: 将项目目录树字符串转换为JSON结构
Home-page: https://github.com/Knighthood2001/Python-tree2json
Author: knighthood2001
License: UNKNOWN
Platform: UNKNOWN
Classifier: Programming Language :: Python :: 3
Classifier: License :: OSI Approved :: MIT License
Requires-Python: >=3.6
